textfx/__init__.py
textfx/loading.py
textfx/textfx.py
textfx/untextfx.py
textfx-2.4.3.dist-info/licenses/LICENSE
textfx-2.4.3.dist-info/METADATA
textfx-2.4.3.dist-info/WHEEL
textfx-2.4.3.dist-info/top_level.txt
textfx-2.4.3.dist-info/RECORD
